{
  "pdf_path": "C:\\Projects\\backbone_skeleton\\test.pdf",
  "dpi": 200,
  "pages": {
    "13": {
      "image_width_px": 6800,
      "image_height_px": 4400,
      "boxes": [
        {
          "id": 1,
          "bbox_px": [
            299,
            98,
            6268,
            4302
          ],
          "bbox_pdf": [
            107.64,
            35.28,
            2256.48,
            1548.72
          ],
          "area_frac": 0.8386923796791443,
          "is_page_border_hint": false
        },
        {
          "id": 2,
          "bbox_px": [
            303,
            103,
            6263,
            4297
          ],
          "bbox_pdf": [
            109.08,
            37.08,
            2254.68,
            1546.9199999999998
          ],
          "area_frac": 0.8354358288770053,
          "is_page_border_hint": false
        },
        {
          "id": 3,
          "bbox_px": [
            2573,
            2736,
            4164,
            3903
          ],
          "bbox_pdf": [
            926.28,
            984.9599999999999,
            1499.04,
            1405.08
          ],
          "area_frac": 0.06205538101604278,
          "is_page_border_hint": false
        },
        {
          "id": 4,
          "bbox_px": [
            6312,
            98,
            6702,
            4302
          ],
          "bbox_pdf": [
            2272.3199999999997,
            35.28,
            2412.72,
            1548.72
          ],
          "area_frac": 0.05479812834224599,
          "is_page_border_hint": false
        },
        {
          "id": 5,
          "bbox_px": [
            1642,
            401,
            2830,
            1754
          ],
          "bbox_pdf": [
            591.12,
            144.35999999999999,
            1018.8,
            631.4399999999999
          ],
          "area_frac": 0.053722058823529414,
          "is_page_border_hint": false
        },
        {
          "id": 6,
          "bbox_px": [
            4796,
            2870,
            5712,
            3597
          ],
          "bbox_pdf": [
            1726.56,
            1033.2,
            2056.3199999999997,
            1294.9199999999998
          ],
          "area_frac": 0.022257085561497327,
          "is_page_border_hint": false
        },
        {
          "id": 7,
          "bbox_px": [
            3304,
            624,
            4187,
            1186
          ],
          "bbox_pdf": [
            1189.44,
            224.64,
            1507.32,
            426.96
          ],
          "area_frac": 0.01658576203208556,
          "is_page_border_hint": false
        },
        {
          "id": 8,
          "bbox_px": [
            2067,
            883,
            2703,
            1566
          ],
          "bbox_pdf": [
            744.12,
            317.88,
            973.0799999999999,
            563.76
          ],
          "area_frac": 0.014518315508021391,
          "is_page_border_hint": false
        },
        {
          "id": 9,
          "bbox_px": [
            2723,
            3330,
            3718,
            3725
          ],
          "bbox_pdf": [
            980.28,
            1198.8,
            1338.48,
            1341.0
          ],
          "area_frac": 0.01313586229946524,
          "is_page_border_hint": false
        },
        {
          "id": 10,
          "bbox_px": [
            6317,
            2943,
            6697,
            3941
          ],
          "bbox_pdf": [
            2274.12,
            1059.48,
            2410.92,
            1418.76
          ],
          "area_frac": 0.012675133689839573,
          "is_page_border_hint": false
        },
        {
          "id": 11,
          "bbox_px": [
            1119,
            3182,
            2003,
            3597
          ],
          "bbox_pdf": [
            402.84,
            1145.52,
            721.0799999999999,
            1294.9199999999998
          ],
          "area_frac": 0.012261363636363636,
          "is_page_border_hint": false
        },
        {
          "id": 12,
          "bbox_px": [
            5001,
            3197,
            5708,
            3544
          ],
          "bbox_pdf": [
            1800.36,
            1150.9199999999998,
            2054.88,
            1275.84
          ],
          "area_frac": 0.008199498663101604,
          "is_page_border_hint": false
        },
        {
          "id": 13,
          "bbox_px": [
            1387,
            3197,
            2000,
            3544
          ],
          "bbox_pdf": [
            499.32,
            1150.9199999999998,
            720.0,
            1275.84
          ],
          "area_frac": 0.00710932486631016,
          "is_page_border_hint": false
        },
        {
          "id": 14,
          "bbox_px": [
            6317,
            103,
            6697,
            646
          ],
          "bbox_pdf": [
            2274.12,
            37.08,
            2410.92,
            232.56
          ],
          "area_frac": 0.006896390374331551,
          "is_page_border_hint": false
        },
        {
          "id": 15,
          "bbox_px": [
            6317,
            650,
            6696,
            1130
          ],
          "bbox_pdf": [
            2274.12,
            234.0,
            2410.56,
            406.8
          ],
          "area_frac": 0.0060802139037433155,
          "is_page_border_hint": false
        },
        {
          "id": 16,
          "bbox_px": [
            4531,
            3975,
            5860,
            4105
          ],
          "bbox_pdf": [
            1631.1599999999999,
            1431.0,
            2109.6,
            1477.8
          ],
          "area_frac": 0.005774398395721925,
          "is_page_border_hint": false
        },
        {
          "id": 17,
          "bbox_px": [
            1508,
            1814,
            2837,
            1944
          ],
          "bbox_pdf": [
            542.88,
            653.04,
            1021.3199999999999,
            699.8399999999999
          ],
          "area_frac": 0.005774398395721925,
          "is_page_border_hint": false
        },
        {
          "id": 18,
          "bbox_px": [
            3303,
            3326,
            3722,
            3726
          ],
          "bbox_pdf": [
            1189.08,
            1197.36,
            1339.9199999999998,
            1341.36
          ],
          "area_frac": 0.0056016042780748666,
          "is_page_border_hint": false
        },
        {
          "id": 19,
          "bbox_px": [
            2071,
            1169,
            2466,
            1564
          ],
          "bbox_pdf": [
            745.56,
            420.84,
            887.76,
            563.04
          ],
          "area_frac": 0.005214739304812834,
          "is_page_border_hint": false
        },
        {
          "id": 20,
          "bbox_px": [
            1738,
            1039,
            2032,
            1569
          ],
          "bbox_pdf": [
            625.68,
            374.03999999999996,
            731.52,
            564.84
          ],
          "area_frac": 0.005207887700534759,
          "is_page_border_hint": false
        },
        {
          "id": 21,
          "bbox_px": [
            3307,
            884,
            4184,
            1034
          ],
          "bbox_pdf": [
            1190.52,
            318.24,
            1506.24,
            372.24
          ],
          "area_frac": 0.004396724598930481,
          "is_page_border_hint": false
        },
        {
          "id": 22,
          "bbox_px": [
            6317,
            1308,
            6697,
            1636
          ],
          "bbox_pdf": [
            2274.12,
            470.88,
            2410.92,
            588.9599999999999
          ],
          "area_frac": 0.004165775401069519,
          "is_page_border_hint": false
        },
        {
          "id": 23,
          "bbox_px": [
            2732,
            4116,
            4061,
            4193
          ],
          "bbox_pdf": [
            983.52,
            1481.76,
            1461.96,
            1509.48
          ],
          "area_frac": 0.003420220588235294,
          "is_page_border_hint": false
        },
        {
          "id": 24,
          "bbox_px": [
            870,
            4116,
            2199,
            4193
          ],
          "bbox_pdf": [
            313.2,
            1481.76,
            791.64,
            1509.48
          ],
          "area_frac": 0.003420220588235294,
          "is_page_border_hint": false
        },
        {
          "id": 25,
          "bbox_px": [
            3184,
            1867,
            4513,
            1944
          ],
          "bbox_pdf": [
            1146.24,
            672.12,
            1624.6799999999998,
            699.8399999999999
          ],
          "area_frac": 0.003420220588235294,
          "is_page_border_hint": false
        },
        {
          "id": 26,
          "bbox_px": [
            3302,
            3197,
            4075,
            3325
          ],
          "bbox_pdf": [
            1188.72,
            1150.9199999999998,
            1467.0,
            1197.0
          ],
          "area_frac": 0.003306951871657754,
          "is_page_border_hint": false
        },
        {
          "id": 27,
          "bbox_px": [
            5004,
            2788,
            5246,
            3194
          ],
          "bbox_pdf": [
            1801.4399999999998,
            1003.68,
            1888.56,
            1149.84
          ],
          "area_frac": 0.003283823529411765,
          "is_page_border_hint": false
        },
        {
          "id": 28,
          "bbox_px": [
            2071,
            1036,
            2703,
            1164
          ],
          "bbox_pdf": [
            745.56,
            372.96,
            973.0799999999999,
            419.03999999999996
          ],
          "area_frac": 0.0027037433155080214,
          "is_page_border_hint": false
        },
        {
          "id": 29,
          "bbox_px": [
            6317,
            3945,
            6697,
            4152
          ],
          "bbox_pdf": [
            2274.12,
            1420.2,
            2410.92,
            1494.72
          ],
          "area_frac": 0.002629010695187166,
          "is_page_border_hint": false
        },
        {
          "id": 30,
          "bbox_px": [
            6317,
            1640,
            6420,
            2395
          ],
          "bbox_pdf": [
            2274.12,
            590.4,
            2311.2,
            862.1999999999999
          ],
          "area_frac": 0.0025990975935828876,
          "is_page_border_hint": false
        },
        {
          "id": 31,
          "bbox_px": [
            1141,
            3280,
            1382,
            3593
          ],
          "bbox_pdf": [
            410.76,
            1180.8,
            497.52,
            1293.48
          ],
          "area_frac": 0.0025211564171122997,
          "is_page_border_hint": false
        },
        {
          "id": 32,
          "bbox_px": [
            4996,
            3606,
            5268,
            3863
          ],
          "bbox_pdf": [
            1798.56,
            1298.1599999999999,
            1896.48,
            1390.6799999999998
          ],
          "area_frac": 0.0023363636363636364,
          "is_page_border_hint": false
        },
        {
          "id": 33,
          "bbox_px": [
            1382,
            3606,
            1654,
            3863
          ],
          "bbox_pdf": [
            497.52,
            1298.1599999999999,
            595.4399999999999,
            1390.6799999999998
          ],
          "area_frac": 0.0023363636363636364,
          "is_page_border_hint": false
        },
        {
          "id": 34,
          "bbox_px": [
            6317,
            1134,
            6697,
            1301
          ],
          "bbox_pdf": [
            2274.12,
            408.24,
            2410.92,
            468.35999999999996
          ],
          "area_frac": 0.002120989304812834,
          "is_page_border_hint": false
        },
        {
          "id": 35,
          "bbox_px": [
            6367,
            1315,
            6656,
            1519
          ],
          "bbox_pdf": [
            2292.12,
            473.4,
            2396.16,
            546.84
          ],
          "area_frac": 0.0019704545454545456,
          "is_page_border_hint": false
        },
        {
          "id": 36,
          "bbox_px": [
            6317,
            4156,
            6697,
            4297
          ],
          "bbox_pdf": [
            2274.12,
            1496.1599999999999,
            2410.92,
            1546.9199999999998
          ],
          "area_frac": 0.0017907754010695186,
          "is_page_border_hint": false
        },
        {
          "id": 37,
          "bbox_px": [
            6403,
            1270,
            6615,
            1482
          ],
          "bbox_pdf": [
            2305.08,
            457.2,
            2381.4,
            533.52
          ],
          "area_frac": 0.001502139037433155,
          "is_page_border_hint": false
        },
        {
          "id": 38,
          "bbox_px": [
            3307,
            1036,
            3788,
            1114
          ],
          "bbox_pdf": [
            1190.52,
            372.96,
            1363.6799999999998,
            401.03999999999996
          ],
          "area_frac": 0.0012539438502673797,
          "is_page_border_hint": false
        },
        {
          "id": 39,
          "bbox_px": [
            3760,
            1036,
            4184,
            1114
          ],
          "bbox_pdf": [
            1353.6,
            372.96,
            1506.24,
            401.03999999999996
          ],
          "area_frac": 0.0011053475935828877,
          "is_page_border_hint": false
        },
        {
          "id": 40,
          "bbox_px": [
            6317,
            2399,
            6420,
            2719
          ],
          "bbox_pdf": [
            2274.12,
            863.64,
            2311.2,
            978.8399999999999
          ],
          "area_frac": 0.0011016042780748663,
          "is_page_border_hint": false
        },
        {
          "id": 41,
          "bbox_px": [
            6348,
            418,
            6527,
            597
          ],
          "bbox_pdf": [
            2285.2799999999997,
            150.48,
            2349.72,
            214.92
          ],
          "area_frac": 0.001070889037433155,
          "is_page_border_hint": false
        },
        {
          "id": 42,
          "bbox_px": [
            1666,
            712,
            2043,
            795
          ],
          "bbox_pdf": [
            599.76,
            256.32,
            735.48,
            286.2
          ],
          "area_frac": 0.001045822192513369,
          "is_page_border_hint": false
        },
        {
          "id": 43,
          "bbox_px": [
            6349,
            420,
            6525,
            595
          ],
          "bbox_pdf": [
            2285.64,
            151.2,
            2349.0,
            214.2
          ],
          "area_frac": 0.0010294117647058824,
          "is_page_border_hint": false
        },
        {
          "id": 44,
          "bbox_px": [
            6640,
            1790,
            6697,
            2303
          ],
          "bbox_pdf": [
            2390.4,
            644.4,
            2410.92,
            829.0799999999999
          ],
          "area_frac": 0.0009773061497326202,
          "is_page_border_hint": false
        },
        {
          "id": 45,
          "bbox_px": [
            6353,
            423,
            6522,
            592
          ],
          "bbox_pdf": [
            2287.08,
            152.28,
            2347.92,
            213.12
          ],
          "area_frac": 0.0009545788770053476,
          "is_page_border_hint": false
        },
        {
          "id": 46,
          "bbox_px": [
            6355,
            425,
            6520,
            590
          ],
          "bbox_pdf": [
            2287.7999999999997,
            153.0,
            2347.2,
            212.4
          ],
          "area_frac": 0.0009099264705882353,
          "is_page_border_hint": false
        },
        {
          "id": 47,
          "bbox_px": [
            3701,
            886,
            3879,
            1031
          ],
          "bbox_pdf": [
            1332.36,
            318.96,
            1396.44,
            371.15999999999997
          ],
          "area_frac": 0.0008626336898395722,
          "is_page_border_hint": false
        },
        {
          "id": 48,
          "bbox_px": [
            2071,
            886,
            2249,
            1031
          ],
          "bbox_pdf": [
            745.56,
            318.96,
            809.64,
            371.15999999999997
          ],
          "area_frac": 0.0008626336898395722,
          "is_page_border_hint": false
        },
        {
          "id": 49,
          "bbox_px": [
            3118,
            2562,
            3224,
            2789
          ],
          "bbox_pdf": [
            1122.48,
            922.3199999999999,
            1160.6399999999999,
            1004.04
          ],
          "area_frac": 0.000804211229946524,
          "is_page_border_hint": false
        },
        {
          "id": 50,
          "bbox_px": [
            4946,
            2562,
            5051,
            2790
          ],
          "bbox_pdf": [
            1780.56,
            922.3199999999999,
            1818.36,
            1004.4
          ],
          "area_frac": 0.0008001336898395721,
          "is_page_border_hint": false
        },
        {
          "id": 51,
          "bbox_px": [
            1332,
            2562,
            1437,
            2790
          ],
          "bbox_pdf": [
            479.52,
            922.3199999999999,
            517.3199999999999,
            1004.4
          ],
          "area_frac": 0.0008001336898395721,
          "is_page_border_hint": false
        },
        {
          "id": 52,
          "bbox_px": [
            3737,
            401,
            3843,
            611
          ],
          "bbox_pdf": [
            1345.32,
            144.35999999999999,
            1383.48,
            219.95999999999998
          ],
          "area_frac": 0.0007439839572192514,
          "is_page_border_hint": false
        },
        {
          "id": 53,
          "bbox_px": [
            6317,
            2723,
            6420,
            2939
          ],
          "bbox_pdf": [
            2274.12,
            980.28,
            2311.2,
            1058.04
          ],
          "area_frac": 0.0007435828877005347,
          "is_page_border_hint": false
        },
        {
          "id": 54,
          "bbox_px": [
            6361,
            446,
            6513,
            584
          ],
          "bbox_pdf": [
            2289.96,
            160.56,
            2344.68,
            210.23999999999998
          ],
          "area_frac": 0.0007010695187165775,
          "is_page_border_hint": false
        },
        {
          "id": 55,
          "bbox_px": [
            6363,
            449,
            6511,
            581
          ],
          "bbox_pdf": [
            2290.68,
            161.64,
            2343.96,
            209.16
          ],
          "area_frac": 0.0006529411764705882,
          "is_page_border_hint": false
        },
        {
          "id": 56,
          "bbox_px": [
            6639,
            2399,
            6697,
            2719
          ],
          "bbox_pdf": [
            2390.04,
            863.64,
            2410.92,
            978.8399999999999
          ],
          "area_frac": 0.0006203208556149732,
          "is_page_border_hint": false
        },
        {
          "id": 57,
          "bbox_px": [
            6604,
            1790,
            6636,
            2303
          ],
          "bbox_pdf": [
            2377.44,
            644.4,
            2388.96,
            829.0799999999999
          ],
          "area_frac": 0.0005486631016042781,
          "is_page_border_hint": false
        },
        {
          "id": 58,
          "bbox_px": [
            6568,
            1790,
            6600,
            2303
          ],
          "bbox_pdf": [
            2364.48,
            644.4,
            2376.0,
            829.0799999999999
          ],
          "area_frac": 0.0005486631016042781,
          "is_page_border_hint": false
        },
        {
          "id": 59,
          "bbox_px": [
            6532,
            1790,
            6564,
            2303
          ],
          "bbox_pdf": [
            2351.52,
            644.4,
            2363.04,
            829.0799999999999
          ],
          "area_frac": 0.0005486631016042781,
          "is_page_border_hint": false
        },
        {
          "id": 60,
          "bbox_px": [
            6496,
            1790,
            6528,
            2303
          ],
          "bbox_pdf": [
            2338.56,
            644.4,
            2350.08,
            829.0799999999999
          ],
          "area_frac": 0.0005486631016042781,
          "is_page_border_hint": false
        },
        {
          "id": 61,
          "bbox_px": [
            6460,
            1790,
            6492,
            2303
          ],
          "bbox_pdf": [
            2325.6,
            644.4,
            2337.12,
            829.0799999999999
          ],
          "area_frac": 0.0005486631016042781,
          "is_page_border_hint": false
        },
        {
          "id": 62,
          "bbox_px": [
            6424,
            1790,
            6456,
            2303
          ],
          "bbox_pdf": [
            2312.64,
            644.4,
            2324.16,
            829.0799999999999
          ],
          "area_frac": 0.0005486631016042781,
          "is_page_border_hint": false
        },
        {
          "id": 63,
          "bbox_px": [
            6385,
            1223,
            6613,
            1292
          ],
          "bbox_pdf": [
            2298.6,
            440.28,
            2380.68,
            465.12
          ],
          "area_frac": 0.0005258021390374332,
          "is_page_border_hint": false
        }
      ]
    }
  }
}