{
  "pdf_path": "test.pdf",
  "dpi": 200,
  "pages": {
    "3": {
      "image_width_px": 6800,
      "image_height_px": 4400,
      "boxes": [
        {
          "id": 1,
          "bbox_px": [
            296,
            96,
            6703,
            4303
          ],
          "bbox_pdf": [
            106.56,
            34.56,
            2413.08,
            1549.08
          ],
          "area_frac": 0.9008773061497326,
          "is_page_border_hint": false
        },
        {
          "id": 2,
          "bbox_px": [
            298,
            99,
            6268,
            4301
          ],
          "bbox_pdf": [
            107.28,
            35.64,
            2256.48,
            1548.36
          ],
          "area_frac": 0.8384338235294118,
          "is_page_border_hint": false
        },
        {
          "id": 3,
          "bbox_px": [
            303,
            103,
            6263,
            4297
          ],
          "bbox_pdf": [
            109.08,
            37.08,
            2254.68,
            1546.9199999999998
          ],
          "area_frac": 0.8354358288770053,
          "is_page_border_hint": false
        },
        {
          "id": 4,
          "bbox_px": [
            1457,
            3335,
            5181,
            4297
          ],
          "bbox_pdf": [
            524.52,
            1200.6,
            1865.1599999999999,
            1546.9199999999998
          ],
          "area_frac": 0.1197355614973262,
          "is_page_border_hint": false
        },
        {
          "id": 5,
          "bbox_px": [
            1460,
            3338,
            2833,
            4294
          ],
          "bbox_pdf": [
            525.6,
            1201.68,
            1019.88,
            1545.84
          ],
          "area_frac": 0.04386991978609626,
          "is_page_border_hint": false
        },
        {
          "id": 6,
          "bbox_px": [
            6314,
            1338,
            6701,
            4302
          ],
          "bbox_pdf": [
            2273.04,
            481.68,
            2412.36,
            1548.72
          ],
          "area_frac": 0.03833783422459893,
          "is_page_border_hint": false
        },
        {
          "id": 7,
          "bbox_px": [
            2837,
            3338,
            3711,
            4294
          ],
          "bbox_pdf": [
            1021.3199999999999,
            1201.68,
            1335.96,
            1545.84
          ],
          "area_frac": 0.027925935828877004,
          "is_page_border_hint": false
        },
        {
          "id": 8,
          "bbox_px": [
            3716,
            3338,
            4521,
            4294
          ],
          "bbox_pdf": [
            1337.76,
            1201.68,
            1627.56,
            1545.84
          ],
          "area_frac": 0.02572125668449198,
          "is_page_border_hint": false
        },
        {
          "id": 9,
          "bbox_px": [
            4526,
            3338,
            5178,
            4294
          ],
          "bbox_pdf": [
            1629.36,
            1201.68,
            1864.08,
            1545.84
          ],
          "area_frac": 0.020832620320855616,
          "is_page_border_hint": false
        },
        {
          "id": 10,
          "bbox_px": [
            6317,
            1639,
            6699,
            2940
          ],
          "bbox_pdf": [
            2274.12,
            590.04,
            2411.64,
            1058.3999999999999
          ],
          "area_frac": 0.016610360962566843,
          "is_page_border_hint": false
        },
        {
          "id": 11,
          "bbox_px": [
            6314,
            98,
            6701,
            1319
          ],
          "bbox_pdf": [
            2273.04,
            35.28,
            2412.36,
            474.84
          ],
          "area_frac": 0.015793014705882354,
          "is_page_border_hint": false
        },
        {
          "id": 12,
          "bbox_px": [
            6317,
            2942,
            6699,
            3943
          ],
          "bbox_pdf": [
            2274.12,
            1059.12,
            2411.64,
            1419.48
          ],
          "area_frac": 0.01278014705882353,
          "is_page_border_hint": false
        },
        {
          "id": 13,
          "bbox_px": [
            6319,
            2944,
            6697,
            3941
          ],
          "bbox_pdf": [
            2274.8399999999997,
            1059.84,
            2410.92,
            1418.76
          ],
          "area_frac": 0.012595788770053476,
          "is_page_border_hint": false
        },
        {
          "id": 14,
          "bbox_px": [
            1460,
            3220,
            5178,
            3283
          ],
          "bbox_pdf": [
            525.6,
            1159.2,
            1864.08,
            1181.8799999999999
          ],
          "area_frac": 0.007828676470588235,
          "is_page_border_hint": false
        },
        {
          "id": 15,
          "bbox_px": [
            5521,
            3505,
            5988,
            3972
          ],
          "bbox_pdf": [
            1987.56,
            1261.8,
            2155.68,
            1429.9199999999998
          ],
          "area_frac": 0.007289070855614973,
          "is_page_border_hint": false
        },
        {
          "id": 16,
          "bbox_px": [
            5523,
            3506,
            5986,
            3971
          ],
          "bbox_pdf": [
            1988.28,
            1262.1599999999999,
            2154.96,
            1429.56
          ],
          "area_frac": 0.007195688502673797,
          "is_page_border_hint": false
        },
        {
          "id": 17,
          "bbox_px": [
            6317,
            610,
            6699,
            1155
          ],
          "bbox_pdf": [
            2274.12,
            219.6,
            2411.64,
            415.8
          ],
          "area_frac": 0.00695822192513369,
          "is_page_border_hint": false
        },
        {
          "id": 18,
          "bbox_px": [
            6319,
            611,
            6697,
            1153
          ],
          "bbox_pdf": [
            2274.8399999999997,
            219.95999999999998,
            2410.92,
            415.08
          ],
          "area_frac": 0.006847459893048129,
          "is_page_border_hint": false
        },
        {
          "id": 19,
          "bbox_px": [
            5532,
            3515,
            5977,
            3962
          ],
          "bbox_pdf": [
            1991.52,
            1265.3999999999999,
            2151.72,
            1426.32
          ],
          "area_frac": 0.0066482286096256685,
          "is_page_border_hint": false
        },
        {
          "id": 20,
          "bbox_px": [
            5533,
            3517,
            5976,
            3960
          ],
          "bbox_pdf": [
            1991.8799999999999,
            1266.12,
            2151.36,
            1425.6
          ],
          "area_frac": 0.006559124331550802,
          "is_page_border_hint": false
        },
        {
          "id": 21,
          "bbox_px": [
            6319,
            103,
            6697,
            605
          ],
          "bbox_pdf": [
            2274.8399999999997,
            37.08,
            2410.92,
            217.79999999999998
          ],
          "area_frac": 0.00634211229946524,
          "is_page_border_hint": false
        },
        {
          "id": 22,
          "bbox_px": [
            1460,
            3290,
            5178,
            3333
          ],
          "bbox_pdf": [
            525.6,
            1184.3999999999999,
            1864.08,
            1199.8799999999999
          ],
          "area_frac": 0.005343382352941176,
          "is_page_border_hint": false
        },
        {
          "id": 23,
          "bbox_px": [
            6317,
            3945,
            6699,
            4153
          ],
          "bbox_pdf": [
            2274.12,
            1420.2,
            2411.64,
            1495.08
          ],
          "area_frac": 0.002655614973262032,
          "is_page_border_hint": false
        },
        {
          "id": 24,
          "bbox_px": [
            6319,
            3947,
            6697,
            4152
          ],
          "bbox_pdf": [
            2274.8399999999997,
            1420.9199999999998,
            2410.92,
            1494.72
          ],
          "area_frac": 0.0025899064171122995,
          "is_page_border_hint": false
        },
        {
          "id": 25,
          "bbox_px": [
            6319,
            1641,
            6421,
            2395
          ],
          "bbox_pdf": [
            2274.8399999999997,
            590.76,
            2311.56,
            862.1999999999999
          ],
          "area_frac": 0.0025704545454545455,
          "is_page_border_hint": false
        },
        {
          "id": 26,
          "bbox_px": [
            6303,
            1159,
            6697,
            1330
          ],
          "bbox_pdf": [
            2269.08,
            417.24,
            2410.92,
            478.79999999999995
          ],
          "area_frac": 0.0022518048128342245,
          "is_page_border_hint": false
        },
        {
          "id": 27,
          "bbox_px": [
            6317,
            4156,
            6699,
            4299
          ],
          "bbox_pdf": [
            2274.12,
            1496.1599999999999,
            2411.64,
            1547.6399999999999
          ],
          "area_frac": 0.0018257352941176471,
          "is_page_border_hint": false
        },
        {
          "id": 28,
          "bbox_px": [
            6319,
            4157,
            6697,
            4297
          ],
          "bbox_pdf": [
            2274.8399999999997,
            1496.52,
            2410.92,
            1546.9199999999998
          ],
          "area_frac": 0.001768716577540107,
          "is_page_border_hint": false
        },
        {
          "id": 29,
          "bbox_px": [
            3334,
            167,
            4311,
            218
          ],
          "bbox_pdf": [
            1200.24,
            60.12,
            1551.96,
            78.48
          ],
          "area_frac": 0.001665340909090909,
          "is_page_border_hint": false
        },
        {
          "id": 30,
          "bbox_px": [
            6372,
            1335,
            6645,
            1509
          ],
          "bbox_pdf": [
            2293.92,
            480.59999999999997,
            2392.2,
            543.24
          ],
          "area_frac": 0.0015876336898395722,
          "is_page_border_hint": false
        },
        {
          "id": 31,
          "bbox_px": [
            5652,
            3662,
            5858,
            3869
          ],
          "bbox_pdf": [
            2034.72,
            1318.32,
            2108.88,
            1392.84
          ],
          "area_frac": 0.0014252005347593583,
          "is_page_border_hint": false
        },
        {
          "id": 32,
          "bbox_px": [
            5654,
            3664,
            5856,
            3867
          ],
          "bbox_pdf": [
            2035.4399999999998,
            1319.04,
            2108.16,
            1392.12
          ],
          "area_frac": 0.0013705213903743316,
          "is_page_border_hint": false
        },
        {
          "id": 33,
          "bbox_px": [
            6403,
            1236,
            6638,
            1378
          ],
          "bbox_pdf": [
            2305.08,
            444.96,
            2389.68,
            496.08
          ],
          "area_frac": 0.0011153074866310161,
          "is_page_border_hint": false
        },
        {
          "id": 34,
          "bbox_px": [
            6319,
            2399,
            6421,
            2719
          ],
          "bbox_pdf": [
            2274.8399999999997,
            863.64,
            2311.56,
            978.8399999999999
          ],
          "area_frac": 0.001090909090909091,
          "is_page_border_hint": false
        },
        {
          "id": 35,
          "bbox_px": [
            6349,
            398,
            6527,
            576
          ],
          "bbox_pdf": [
            2285.64,
            143.28,
            2349.72,
            207.35999999999999
          ],
          "area_frac": 0.0010589572192513368,
          "is_page_border_hint": false
        },
        {
          "id": 36,
          "bbox_px": [
            6350,
            399,
            6526,
            575
          ],
          "bbox_pdf": [
            2286.0,
            143.64,
            2349.36,
            207.0
          ],
          "area_frac": 0.0010352941176470587,
          "is_page_border_hint": false
        },
        {
          "id": 37,
          "bbox_px": [
            6640,
            1790,
            6697,
            2304
          ],
          "bbox_pdf": [
            2390.4,
            644.4,
            2410.92,
            829.4399999999999
          ],
          "area_frac": 0.000979211229946524,
          "is_page_border_hint": false
        },
        {
          "id": 38,
          "bbox_px": [
            6355,
            403,
            6522,
            570
          ],
          "bbox_pdf": [
            2287.7999999999997,
            145.07999999999998,
            2347.92,
            205.2
          ],
          "area_frac": 0.0009321189839572192,
          "is_page_border_hint": false
        },
        {
          "id": 39,
          "bbox_px": [
            6356,
            405,
            6520,
            569
          ],
          "bbox_pdf": [
            2288.16,
            145.79999999999998,
            2347.2,
            204.84
          ],
          "area_frac": 0.0008989304812834224,
          "is_page_border_hint": false
        },
        {
          "id": 40,
          "bbox_px": [
            6319,
            2723,
            6421,
            2938
          ],
          "bbox_pdf": [
            2274.8399999999997,
            980.28,
            2311.56,
            1057.68
          ],
          "area_frac": 0.0007329545454545454,
          "is_page_border_hint": false
        },
        {
          "id": 41,
          "bbox_px": [
            6362,
            425,
            6514,
            563
          ],
          "bbox_pdf": [
            2290.3199999999997,
            153.0,
            2345.04,
            202.67999999999998
          ],
          "area_frac": 0.0007010695187165775,
          "is_page_border_hint": false
        },
        {
          "id": 42,
          "bbox_px": [
            6364,
            427,
            6512,
            561
          ],
          "bbox_pdf": [
            2291.04,
            153.72,
            2344.3199999999997,
            201.95999999999998
          ],
          "area_frac": 0.0006628342245989304,
          "is_page_border_hint": false
        },
        {
          "id": 43,
          "bbox_px": [
            6640,
            2399,
            6697,
            2719
          ],
          "bbox_pdf": [
            2390.4,
            863.64,
            2410.92,
            978.8399999999999
          ],
          "area_frac": 0.0006096256684491978,
          "is_page_border_hint": false
        },
        {
          "id": 44,
          "bbox_px": [
            4238,
            3843,
            4316,
            4054
          ],
          "bbox_pdf": [
            1525.6799999999998,
            1383.48,
            1553.76,
            1459.44
          ],
          "area_frac": 0.0005500668449197861,
          "is_page_border_hint": false
        },
        {
          "id": 45,
          "bbox_px": [
            6604,
            1790,
            6636,
            2304
          ],
          "bbox_pdf": [
            2377.44,
            644.4,
            2388.96,
            829.4399999999999
          ],
          "area_frac": 0.0005497326203208556,
          "is_page_border_hint": false
        },
        {
          "id": 46,
          "bbox_px": [
            6568,
            1790,
            6600,
            2304
          ],
          "bbox_pdf": [
            2364.48,
            644.4,
            2376.0,
            829.4399999999999
          ],
          "area_frac": 0.0005497326203208556,
          "is_page_border_hint": false
        },
        {
          "id": 47,
          "bbox_px": [
            6532,
            1790,
            6564,
            2304
          ],
          "bbox_pdf": [
            2351.52,
            644.4,
            2363.04,
            829.4399999999999
          ],
          "area_frac": 0.0005497326203208556,
          "is_page_border_hint": false
        },
        {
          "id": 48,
          "bbox_px": [
            6496,
            1790,
            6528,
            2304
          ],
          "bbox_pdf": [
            2338.56,
            644.4,
            2350.08,
            829.4399999999999
          ],
          "area_frac": 0.0005497326203208556,
          "is_page_border_hint": false
        },
        {
          "id": 49,
          "bbox_px": [
            6425,
            1790,
            6457,
            2304
          ],
          "bbox_pdf": [
            2313.0,
            644.4,
            2324.52,
            829.4399999999999
          ],
          "area_frac": 0.0005497326203208556,
          "is_page_border_hint": false
        },
        {
          "id": 50,
          "bbox_px": [
            6461,
            1790,
            6492,
            2304
          ],
          "bbox_pdf": [
            2325.96,
            644.4,
            2337.12,
            829.4399999999999
          ],
          "area_frac": 0.0005325534759358289,
          "is_page_border_hint": false
        },
        {
          "id": 51,
          "bbox_px": [
            5708,
            3686,
            5834,
            3811
          ],
          "bbox_pdf": [
            2054.88,
            1326.96,
            2100.24,
            1371.96
          ],
          "area_frac": 0.000526403743315508,
          "is_page_border_hint": false
        },
        {
          "id": 52,
          "bbox_px": [
            2385,
            4098,
            2808,
            4135
          ],
          "bbox_pdf": [
            858.6,
            1475.28,
            1010.88,
            1488.6
          ],
          "area_frac": 0.0005230949197860962,
          "is_page_border_hint": false
        },
        {
          "id": 53,
          "bbox_px": [
            2385,
            4058,
            2808,
            4095
          ],
          "bbox_pdf": [
            858.6,
            1460.8799999999999,
            1010.88,
            1474.2
          ],
          "area_frac": 0.0005230949197860962,
          "is_page_border_hint": false
        },
        {
          "id": 54,
          "bbox_px": [
            5676,
            3720,
            5800,
            3843
          ],
          "bbox_pdf": [
            2043.36,
            1339.2,
            2088.0,
            1383.48
          ],
          "area_frac": 0.00050975935828877,
          "is_page_border_hint": false
        }
      ]
    }
  }
}